<?xml version="1.0" encoding="UTF-8"?><retEnviNFe versao="4.00" xmlns="http://www.portalfiscal.inf.br/nfe"><tpAmb>2</tpAmb><verAplic>SP_NFE_PL009_V4</verAplic><cStat>104</cStat><xMotivo>Lote processado</xMotivo><cUF>35</cUF><dhRecbto>2026-06-15T18:50:46-03:00</dhRecbto><protNFe versao="4.00"><infProt><tpAmb>2</tpAmb><verAplic>SP_NFE_PL009_V4</verAplic><chNFe>35260609167426000109550010000086041372213425</chNFe><dhRecbto>2026-06-15T18:50:46-03:00</dhRecbto><nProt>135260005894478</nProt><digVal>PFIYiOW05BVddhvnFGozPl9zPsg=</digVal><cStat>100</cStat><xMotivo>Autorizado o uso da NF-e</xMotivo></infProt></protNFe></retEnviNFe>